odoo/addons/project_tag/README.rst
odoo/addons/project_tag/__init__.py
odoo/addons/project_tag/__manifest__.py
odoo/addons/project_tag/i18n/de.po
odoo/addons/project_tag/i18n/es.po
odoo/addons/project_tag/i18n/fr.po
odoo/addons/project_tag/i18n/it.po
odoo/addons/project_tag/i18n/project_tag.pot
odoo/addons/project_tag/i18n/pt_BR.po
odoo/addons/project_tag/i18n/sl.po
odoo/addons/project_tag/models/__init__.py
odoo/addons/project_tag/models/project.py
odoo/addons/project_tag/readme/CONTRIBUTORS.rst
odoo/addons/project_tag/readme/DESCRIPTION.rst
odoo/addons/project_tag/readme/USAGE.rst
odoo/addons/project_tag/static/description/icon.png
odoo/addons/project_tag/static/description/index.html
odoo/addons/project_tag/views/project.xml
odoo12_addon_project_tag-12.0.1.0.0.99.dev20.dist-info/METADATA
odoo12_addon_project_tag-12.0.1.0.0.99.dev20.dist-info/WHEEL
odoo12_addon_project_tag-12.0.1.0.0.99.dev20.dist-info/top_level.txt
odoo12_addon_project_tag-12.0.1.0.0.99.dev20.dist-info/RECORD
